Workbook
Name quantity: #REF!
Name rate: #REF!

Sheet DashBoards
A1: order_id | B1: date | C1: product | D1: price | E1: quantity | F1: payment_method | G1: Manager | H1: City | I1: Revenue
A2: 1 | B2: 44927 | C2: burgers | D2: 14.99 | E2: 132 | F2: credit card | G2: Garcia | H2: New York | I2: =Orders[[#This Row],[price]]*Orders[[#This Row],[quantity]] -> 1978.68
A3: 2 | B3: 44927 | C3: burgers | D3: 14.99 | E3: 145 | F3: cash | G3: Michael Johnson | H3: San Francisco | I3: =Orders[[#This Row],[price]]*Orders[[#This Row],[quantity]] -> 2173.55 | L3: Column1
A4: 3 | B4: 44927 | C4: burgers | D4: 14.99 | E4: 793 | F4: debit card | G4: Elliot Brooks | H4: Los Angeles | I4: =Orders[[#This Row],[price]]*Orders[[#This Row],[quantity]] -> 11887.07
A5: 4 | B5: 44927 | C5: drinks | D5: 3.99 | E5: 492 | F5: cash | G5: Maria Rodriguez | H5: Miami | I5: =Orders[[#This Row],[price]]*Orders[[#This Row],[quantity]] -> 1963.08 | L5: Mean | M5: 4156.0387
A6: 5 | B6: 44927 | C6: sides and other | D6: 1.99 | E6: 852 | F6: debit card | G6: Elliot Brooks | H6: Atlanta | I6: =Orders[[#This Row],[price]]*Orders[[#This Row],[quantity]] -> 1695.48 | L6: Standard Error | M6: 304.01707
A7: 6 | B7: 44927 | C7: sides and other | D7: 1.99 | E7: 676 | F7: credit card | G7: Elliot Brooks | H7: Miami | I7: =Orders[[#This Row],[price]]*Orders[[#This Row],[quantity]] -> 1345.24 | L7: Median | M7: 3136.335
A8: 7 | B8: 44927 | C8: drinks | D8: 3.99 | E8: 568 | F8: cash | G8: Robert Garcia | H8: San Diego | I8: =Orders[[#This Row],[price]]*Orders[[#This Row],[quantity]] -> 2266.32 | L8: Mode | M8: 6151.2
A9: 8 | B9: 44927 | C9: hot dogs | D9: 6.99 | E9: 611 | F9: debit card | G9: Davis | H9: San Francisco | I9: =Orders[[#This Row],[price]]*Orders[[#This Row],[quantity]] -> 4270.89 | L9: Standard Deviation | M9: 3040.1707
A10: 9 | B10: 44927 | C10: pizzas | D10: 12.99 | E10: 274 | F10: debit card | G10: Priya Desai | H10: New York | I10: =Orders[[#This Row],[price]]*Orders[[#This Row],[quantity]] -> 3559.26 | L10: Sample Variance | M10: 9242638.2
A11: 10 | B11: 44927 | C11: hot dogs | D11: 6.99 | E11: 880 | F11: debit card | G11: Jamal River | H11: Miami | I11: =Orders[[#This Row],[price]]*Orders[[#This Row],[quantity]] -> 6151.2 | L11: Kurtosis | M11: -0.76669639
A12: 11 | B12: 44927 | C12: hot dogs | D12: 6.99 | E12: 880 | F12: debit card | G12: Jamal River | H12: Miami | I12: =Orders[[#This Row],[price]]*Orders[[#This Row],[quantity]] -> 6151.2 | L12: Skewness | M12: 0.71448006
A13: 12 | B13: 44927 | C13: hot dogs | D13: 6.99 | E13: 675 | F13: debit card | G13: Michael Johnson | H13: San Francisco | I13: =Orders[[#This Row],[price]]*Orders[[#This Row],[quantity]] -> 4718.25 | L13: Range | M13: 11397.53
A14: 13 | B14: 44927 | C14: sides and other | D14: 1.99 | E14: 488 | F14: gift card | G14: Maria Rodriguez | H14: San Francisco | I14: =Orders[[#This Row],[price]]*Orders[[#This Row],[quantity]] -> 971.12 | L14: Minimum | M14: 489.54
A15: 14 | B15: 44927 | C15: sides and other | D15: 1.99 | E15: 441 | F15: gift card | G15: Tasha Nguyen | H15: Miami | I15: =Orders[[#This Row],[price]]*Orders[[#This Row],[quantity]] -> 877.59 | L15: Maximum | M15: 11887.07
A16: 15 | B16: 44927 | C16: burgers | D16: 14.99 | E16: 536 | F16: debit card | G16: Tasha Nguyen | H16: New York | I16: =Orders[[#This Row],[price]]*Orders[[#This Row],[quantity]] -> 8034.64 | L16: Sum | M16: 415603.87
A17: 16 | B17: 44928 | C17: burgers | D17: 14.99 | E17: 501 | F17: debit card | G17: Maria Rodriguez | H17: Atlanta | I17: =Orders[[#This Row],[price]]*Orders[[#This Row],[quantity]] -> 7509.99 | L17: Count | M17: 100
A18: 17 | B18: 44928 | C18: pizzas | D18: 12.99 | E18: 177 | F18: cash | G18: Sara Williams | H18: San Francisco | I18: =Orders[[#This Row],[price]]*Orders[[#This Row],[quantity]] -> 2299.23
A19: 18 | B19: 44928 | C19: sides and other | D19: 1.99 | E19: 343 | F19: credit card | G19: Lena Marlowe | H19: Miami | I19: =Orders[[#This Row],[price]]*Orders[[#This Row],[quantity]] -> 682.57
A20: 19 | B20: 44928 | C20: sides and other | D20: 1.99 | E20: 690 | F20: debit card | G20: Anna Davis | H20: Los Angeles | I20: =Orders[[#This Row],[price]]*Orders[[#This Row],[quantity]] -> 1373.1
A21: 20 | B21: 44928 | C21: drinks | D21: 3.99 | E21: 192 | F21: cash | G21: Priya Desai | H21: Miami | I21: =Orders[[#This Row],[price]]*Orders[[#This Row],[quantity]] -> 766.08
A22: 21 | B22: 44928 | C22: hot dogs | D22: 6.99 | E22: 178 | F22: cash | G22: Elliot Brooks | H22: New York | I22: =Orders[[#This Row],[price]]*Orders[[#This Row],[quantity]] -> 1244.22
A23: 22 | B23: 44928 | C23: drinks | D23: 3.99 | E23: 489 | F23: cash | G23: Tasha Nguyen | H23: Boston | I23: =Orders[[#This Row],[price]]*Orders[[#This Row],[quantity]] -> 1951.11
A24: 23 | B24: 44928 | C24: drinks | D24: 3.99 | E24: 487 | F24: debit card | G24: Priya Desai | H24: Los Angeles | I24: =Orders[[#This Row],[price]]*Orders[[#This Row],[quantity]] -> 1943.13
A25: 24 | B25: 44928 | C25: drinks | D25: 3.99 | E25: 347 | F25: debit card | G25: Priya Desai | H25: Los Angeles | I25: =Orders[[#This Row],[price]]*Orders[[#This Row],[quantity]] -> 1384.53
A26: 25 | B26: 44928 | C26: sides and other | D26: 1.99 | E26: 602 | F26: gift card | G26: Anna Davis | H26: Chicago | I26: =Orders[[#This Row],[price]]*Orders[[#This Row],[quantity]] -> 1197.98
A27: 26 | B27: 44928 | C27: burgers | D27: 14.99 | E27: 445 | F27: credit card | G27: Priya Desai | H27: Chicago | I27: =Orders[[#This Row],[price]]*Orders[[#This Row],[quantity]] -> 6670.55
A28: 27 | B28: 44928 | C28: pizzas | D28: 12.99 | E28: 325 | F28: cash | G28: Garcia | H28: New York | I28: =Orders[[#This Row],[price]]*Orders[[#This Row],[quantity]] -> 4221.75
A29: 28 | B29: 44928 | C29: hot dogs | D29: 6.99 | E29: 218 | F29: debit card | G29: Michael Johnson | H29: Atlanta | I29: =Orders[[#This Row],[price]]*Orders[[#This Row],[quantity]] -> 1523.82
... A101: 100 | B101: 44935 | C101: sides and other | D101: 1.99 | E101: 762 | F101: debit card | G101: Lena Marlowe | H101: Los Angeles | I101: =Orders[[#This Row],[price]]*Orders[[#This Row],[quantity]] -> 1516.38

Sheet Sheet2
B2: Row Labels | C2: Sum of Revenue
B3: 44927 | C3: 58043.57
B4: 44928 | C4: 41602.56
B5: 44929 | C5: 46342.08
B6: 44930 | C6: 44815.71
B7: 44931 | C7: 47935.9
B8: 44932 | C8: 42957.09
B9: 44933 | C9: 46031.99
B10: 44934 | C10: 41363.47
B11: 44935 | C11: 46511.5
B19: Row Labels | C19: Sum of Revenue
B20: New York | C20: 86303.44
B21: Miami | C21: 81430.37
B22: San Francisco | C22: 80083.91
B23: Boston | C23: 54360.66
B24: Los Angeles | C24: 50209.38
B25: Chicago | C25: 32658.83
B26: Atlanta | C26: 23523.63
B27: San Diego | C27: 7033.65

Sheet Sheet3
B3: Davis
B4: =SUMIFS(Orders[Revenue],Orders[Manager],Sheet3!$B$3,Orders[product],DashBoards!$C2) -> 6580.61
B5: =SUMIFS(Orders[Revenue],Orders[Manager],Sheet3!$B$3,Orders[product],DashBoards!$C3) -> 6580.61
B6: =SUMIFS(Orders[Revenue],Orders[Manager],Sheet3!$B$3,Orders[product],DashBoards!$C4) -> 6580.61
B7: =SUMIFS(Orders[Revenue],Orders[Manager],Sheet3!$B$3,Orders[product],DashBoards!$C5) -> 1256.85
B8: =SUMIFS(Orders[Revenue],Orders[Manager],Sheet3!$B$3,Orders[product],DashBoards!$C6) -> 0
B9: =SUMIFS(Orders[Revenue],Orders[Manager],Sheet3!$B$3,Orders[product],DashBoards!$C7) -> 0
B10: =SUMIFS(Orders[Revenue],Orders[Manager],Sheet3!$B$3,Orders[product],DashBoards!$C8) -> 1256.85
B11: =SUMIFS(Orders[Revenue],Orders[Manager],Sheet3!$B$3,Orders[product],DashBoards!$C9) -> 14818.8
B12: =SUMIFS(Orders[Revenue],Orders[Manager],Sheet3!$B$3,Orders[product],DashBoards!$C10) -> 5689.62
A13: total | B13: =SUM(B4:B12) -> 42763.95
